{
  "blogs": [
    {
      "id": "1",
      "title": "The first blog",
      "author": "Nidhin",
      "description": "The first messages..."
    },
    {
      "id": "2",
      "title": "Some random title",
      "author": "Shraddha",
      "description": "Some random text"
    },
    {
      "title": "New Title",
      "author": "Varen",
      "description": "More random texts....",
      "id": "j4MGVIr"
    },
    {
      "title": "Dummy",
      "author": "Dummy",
      "description": "Hey",
      "id": "Bai_V1q"
    }
  ]
}